<AinesmileTheme name="javascript" desc="Javascript" ext="">
	<style name="DEFAULT" style_id="41" fg_color="BDAF9D" bg_color="2A211C" font_name="Fixedsys" font_style="0" font_size="10"/>
	<style name="NUMBER" style_id="45" fg_color="FF3A83" bg_color="2A211C" font_name="Fixedsys" font_style="0" font_size="10"/>
	<style name="WORD" style_id="46" fg_color="BDAE9D" bg_color="2A211C" font_name="Fixedsys" font_style="0" font_size="10"/>
	<style name="KEYWORD" style_id="47" fg_color="37A3ED" bg_color="2A211C" font_name="Fixedsys" font_style="0" font_size="10"/>
	<style name="USER-DEFINED" style_id="16" fg_color="FF5555" bg_color="2A211C" font_name="Fixedsys" font_style="0" font_size="10"/>
	<style name="DOUBLESTRING" style_id="48" fg_color="00FF40" bg_color="2A211C" font_name="Fixedsys" font_style="0" font_size="10"/>
	<style name="SINGLESTRING" style_id="49" fg_color="80FF00" bg_color="2A211C" font_name="Fixedsys" font_style="0" font_size="10"/>
	<style name="SYMBOLS" style_id="50" fg_color="E5C138" bg_color="2A211C" font_name="Fixedsys" font_style="0" font_size="10"/>
	<style name="STRINGEOL" style_id="51" fg_color="55E439" bg_color="2A211C" font_name="Fixedsys" font_style="0" font_size="10"/>
	<style name="REGEX" style_id="52" fg_color="FFB454" bg_color="2A211C" font_name="Fixedsys" font_style="0" font_size="10"/>
	<style name="COMMENT" style_id="42" fg_color="666666" bg_color="2A211C" font_name="Fixedsys" font_style="0" font_size="10"/>
	<style name="COMMENTLINE" style_id="43" fg_color="666666" bg_color="2A211C" font_name="Fixedsys" font_style="0" font_size="10"/>
	<style name="COMMENTDOC" style_id="44" fg_color="FFFF80" bg_color="2A211C" font_name="Fixedsys" font_style="0" font_size="10"/>
	<style name="COMMENT DOC KEYWORD" style_id="17" fg_color="FF0080" bg_color="2A211C" font_name="Fixedsys" font_style="0" font_size="10"/>
	<style name="COMMENT DOC KEYWORD ERROR" style_id="18" fg_color="FF0080" bg_color="2A211C" font_name="Fixedsys" font_style="0" font_size="10"/>
</AinesmileTheme>

